nwp_dl_utils/__init__.py
nwp_dl_utils/utils.py
nwp_dl_utils/metno/__init__.py
nwp_dl_utils/metno/meps.py
nwp_dl_utils/metno/mywavewam.py
nwp_dl_utils/metno/norkyst800m.py
nwp_dl_utils-0.0.12.dist-info/METADATA
nwp_dl_utils-0.0.12.dist-info/WHEEL
nwp_dl_utils-0.0.12.dist-info/licenses/LICENSE.txt
nwp_dl_utils-0.0.12.dist-info/RECORD
