Metadata-Version: 2.3
Name: nwp-dl-utils
Version: 0.0.12
Summary: Tools to download (relevant parts of) various NWP products.
Project-URL: Homepage, https://github.com/sintef/nwp-dl-utils
Project-URL: Bug Tracker, https://github.com/sintef/nwp-dl-utils/issues
Author-email: Volker Hoffmann <volker.hoffmann@sintef.no>
License-File: LICENSE.txt
Classifier: Development Status :: 3 - Alpha
Classifier: License :: OSI Approved :: MIT License
Classifier: Operating System :: OS Independent
Classifier: Programming Language :: Python :: 3
Requires-Python: >=3.8
Requires-Dist: dask
Requires-Dist: netcdf4
Requires-Dist: numpy
Requires-Dist: pandas
Requires-Dist: pyresample
Requires-Dist: xarray
